{
    "Statement": [
        {
            "Action": [
                "waf:*",
                "transfer:*",
                "storagegateway:*",
                "states:*",
                "ssm:*",
                "sqs:*",
                "sns:*",
                "ses:*",
                "servicediscovery:*",
                "secretsmanager:*",
                "s3:*",
                "route53:*",
                "redshift:*",
                "rds:*",
                "ram:*",
                "logs:*",
                "lambda:*",
                "kms:*",
                "kafka:*",
                "inspector:*",
                "iam:PassRole",
                "glue:*",
                "glacier:*",
                "firehose:*",
                "events:*",
                "elasticloadbalancing:*",
                "elasticache:*",
                "eks:*",
                "ecs:*",
                "ecr:*",
                "ec2:*",
                "dynamodb:*",
                "cognito-identity:*",
                "cloudwatch:*",
                "cloudtrail:*",
                "cloudfront:*",
                "cloudformation:*",
                "budgets:*",
                "batch:*",
                "autoscaling:*",
                "appsync:*",
                "application-autoscaling:*",
                "apigateway:*"
            ],
            "Effect": "Allow",
            "Resource": "*",
            "Sid": ""
        },
        {
            "Action": [
                "workspaces:*",
                "waf-regional:*",
                "organizations:DescribeOrganization",
                "kinesis:*",
                "iam:UpdateRoleDescription",
                "iam:UpdateAssumeRolePolicy",
                "iam:UpdateAccountPasswordPolicy",
                "iam:UntagRole",
                "iam:TagUser",
                "iam:TagRole",
                "iam:RemoveRoleFromInstanceProfile",
                "iam:PutUserPolicy",
                "iam:PutRolePolicy",
                "iam:ListRoles",
                "iam:ListRolePolicies",
                "iam:ListPolicyVersions",
                "iam:ListPolicies",
                "iam:ListInstanceProfilesForRole",
                "iam:ListInstanceProfiles",
                "iam:ListEntitiesForPolicy",
                "iam:ListAttachedUserPolicies",
                "iam:ListAttachedRolePolicies",
                "iam:ListAccessKeys",
                "iam:GetUserPolicy",
                "iam:GetUser",
                "iam:GetRolePolicy",
                "iam:GetRole",
                "iam:GetPolicyVersion",
                "iam:GetPolicy",
                "iam:GetInstanceProfile",
                "iam:GetAccountPasswordPolicy",
                "iam:DetachUserPolicy",
                "iam:DetachRolePolicy",
                "iam:DeleteUserPolicy",
                "iam:DeleteServiceLinkedRole",
                "iam:DeleteRolePolicy",
                "iam:DeleteRole",
                "iam:DeletePolicyVersion",
                "iam:DeletePolicy",
                "iam:DeleteInstanceProfile",
                "iam:CreateUser",
                "iam:CreateServiceLinkedRole",
                "iam:CreateRole",
                "iam:CreatePolicyVersion",
                "iam:CreatePolicy",
                "iam:CreateInstanceProfile",
                "iam:CreateAccessKey",
                "iam:AttachUserPolicy",
                "iam:AttachRolePolicy",
                "iam:AddRoleToInstanceProfile",
                "es:*",
                "elasticfilesystem:*",
                "ds:*",
                "config:*",
                "cognito-idp:*",
                "cloudformation:*",
                "backup:*",
                "backup-storage:*",
                "acm:*",
                "acm-pca:*"
            ],
            "Effect": "Allow",
            "Resource": "*",
            "Sid": ""
        }
    ],
    "Version": "2012-10-17"
}